isbnlib_kb/__init__.py
isbnlib_kb/_kb.py
isbnlib_kb-0.0.2.dist-info/LICENSE-LGPL.txt
isbnlib_kb-0.0.2.dist-info/METADATA
isbnlib_kb-0.0.2.dist-info/WHEEL
isbnlib_kb-0.0.2.dist-info/entry_points.txt
isbnlib_kb-0.0.2.dist-info/top_level.txt
isbnlib_kb-0.0.2.dist-info/RECORD
