Metadata-Version: 2.1
Name: isbnlib-kb
Version: 0.0.2
Summary: A plugin for isbnlib that pulls metadata from the KB (National Library of the Netherlands).
Home-page: https://github.com/kbNLresearch/isbnlib-kb
Author: willemjan
Author-email: willemjan.faber@kb.nl
License: LGPL v3
Download-URL: https://github.com/kbNLresearch/isbnlib-kb/archive/v0.0.2.zip
Keywords: ISBN isbnlib kb bibliographic-references
Platform: UNKNOWN
Classifier: Programming Language :: Python
Classifier: Programming Language :: Python :: 2
Classifier: Programming Language :: Python :: 2.7
Classifier: Programming Language :: Python :: 3
Classifier: Programming Language :: Python :: 3.4
Classifier: Programming Language :: Python :: 3.5
Classifier: Programming Language :: Python :: 3.6
Classifier: Programming Language :: Python :: 3.7
Classifier: Programming Language :: Python :: 3.8
Classifier: License :: OSI Approved :: GNU Lesser General Public License v3 (LGPLv3)
Classifier: Operating System :: OS Independent
Classifier: Development Status :: 5 - Production/Stable
Classifier: Intended Audience :: Developers
Classifier: Intended Audience :: End Users/Desktop
Classifier: Environment :: Console
Classifier: Topic :: Text Processing :: General
Classifier: Topic :: Software Development :: Libraries :: Python Modules
Requires-Dist: isbnlib (<3.11.0,>=3.9.1)
